streamlit_inspect/__init__.py
streamlit_inspect/classes.py
streamlit_inspect/functions.py
streamlit_inspect-0.1.0.dist-info/METADATA
streamlit_inspect-0.1.0.dist-info/WHEEL
streamlit_inspect-0.1.0.dist-info/top_level.txt
streamlit_inspect-0.1.0.dist-info/RECORD
